odoo9_addon_stock_inventory_lockdown-9.0.1.0.1-py2.7-nspkg.pth
odoo9_addon_stock_inventory_lockdown-9.0.1.0.1.dist-info/DESCRIPTION.rst
odoo9_addon_stock_inventory_lockdown-9.0.1.0.1.dist-info/METADATA
odoo9_addon_stock_inventory_lockdown-9.0.1.0.1.dist-info/RECORD
odoo9_addon_stock_inventory_lockdown-9.0.1.0.1.dist-info/WHEEL
odoo9_addon_stock_inventory_lockdown-9.0.1.0.1.dist-info/metadata.json
odoo9_addon_stock_inventory_lockdown-9.0.1.0.1.dist-info/namespace_packages.txt
odoo9_addon_stock_inventory_lockdown-9.0.1.0.1.dist-info/top_level.txt
odoo_addons/stock_inventory_lockdown/README.rst
odoo_addons/stock_inventory_lockdown/__init__.py
odoo_addons/stock_inventory_lockdown/__openerp__.py
odoo_addons/stock_inventory_lockdown/i18n/de.po
odoo_addons/stock_inventory_lockdown/i18n/es.po
odoo_addons/stock_inventory_lockdown/i18n/es_ES.po
odoo_addons/stock_inventory_lockdown/i18n/fi.po
odoo_addons/stock_inventory_lockdown/i18n/fr.po
odoo_addons/stock_inventory_lockdown/i18n/it.po
odoo_addons/stock_inventory_lockdown/i18n/pt_BR.po
odoo_addons/stock_inventory_lockdown/i18n/ro.po
odoo_addons/stock_inventory_lockdown/i18n/sl.po
odoo_addons/stock_inventory_lockdown/i18n/stock_inventory_lockdown.pot
odoo_addons/stock_inventory_lockdown/i18n/zh_CN.po
odoo_addons/stock_inventory_lockdown/images/move_error.png
odoo_addons/stock_inventory_lockdown/models/__init__.py
odoo_addons/stock_inventory_lockdown/models/stock_inventory.py
odoo_addons/stock_inventory_lockdown/models/stock_location.py
odoo_addons/stock_inventory_lockdown/models/stock_move.py
odoo_addons/stock_inventory_lockdown/tests/__init__.py
odoo_addons/stock_inventory_lockdown/tests/test_stock_inventory_lockdown.py
